semantic_release/__init__.py
semantic_release/ci_checks.py
semantic_release/cli.py
semantic_release/defaults.cfg
semantic_release/errors.py
semantic_release/hvcs.py
semantic_release/pypi.py
semantic_release/settings.py
semantic_release/vcs_helpers.py
semantic_release/history/__init__.py
semantic_release/history/logs.py
semantic_release/history/parser_angular.py
semantic_release/history/parser_helpers.py
semantic_release/history/parser_tag.py
tests/__init__.py
tests/test_cli.py
tests/test_history.py
tests/test_hvcs.py
tests/test_pypi.py
tests/test_settings.py
tests/test_setup_py_hook.py
tests/test_vcs_helpers.py
tests/ci_checks/__init__.py
tests/ci_checks/test_checker.py
tests/ci_checks/test_circle.py
tests/ci_checks/test_frigg.py
tests/ci_checks/test_semaphore.py
tests/ci_checks/test_travis.py
tests/parsers/__init__.py
tests/parsers/test_angular.py
tests/parsers/test_helpers.py
tests/parsers/test_tag.py
python_semantic_release_pypi-3.11.2.dist-info/AUTHORS.rst
python_semantic_release_pypi-3.11.2.dist-info/LICENSE
python_semantic_release_pypi-3.11.2.dist-info/METADATA
python_semantic_release_pypi-3.11.2.dist-info/WHEEL
python_semantic_release_pypi-3.11.2.dist-info/entry_points.txt
python_semantic_release_pypi-3.11.2.dist-info/top_level.txt
python_semantic_release_pypi-3.11.2.dist-info/RECORD
