Metadata-Version: 2.1
Name: python-semantic-release-pypi
Version: 3.11.2
Summary: Automatic semantic versioning for python projects
Home-page: http://github.com/relekang/python-semantic-release
Author: Rolf Erik Lekang
Author-email: me@rolflekang.com
License: MIT
Platform: UNKNOWN
Classifier: Programming Language :: Python
Classifier: Programming Language :: Python :: 2
Classifier: Programming Language :: Python :: 2.7
Classifier: Programming Language :: Python :: 3
Classifier: Programming Language :: Python :: 3.4
Requires-Dist: click (==6.2)
Requires-Dist: gitpython (==2.1.10)
Requires-Dist: invoke (==0.11.1)
Requires-Dist: semver (==2.2.1)
Requires-Dist: twine (==1.11.0)
Requires-Dist: requests (==2.9.1)
Requires-Dist: wheel
